package/Dockerfile
package/__init__.py
package/dockerize.py
package/__pycache__/__init__.cpython-37.pyc
package/templates/Java.Dockerfile
package/templates/NodeJS.Dockerfile
package/templates/Python-Flask.Dockerfile
dockerizeme-0.2.dist-info/METADATA
dockerizeme-0.2.dist-info/WHEEL
dockerizeme-0.2.dist-info/entry_points.txt
dockerizeme-0.2.dist-info/top_level.txt
dockerizeme-0.2.dist-info/RECORD
